sbc_drf_notification/__init__.py
sbc_drf_notification/apps.py
sbc_drf_notification/emailer.py
sbc_drf_notification/factories.py
sbc_drf_notification/mediums.py
sbc_drf_notification/models.py
sbc_drf_notification/settings.py
sbc_drf_notification/signals.py
sbc_drf_notification/tests.py
sbc_drf_notification/migrations/0001_initial.py
sbc_drf_notification/migrations/__init__.py
sbc_drf_notification-1.0.0.dist-info/LICENSE
sbc_drf_notification-1.0.0.dist-info/METADATA
sbc_drf_notification-1.0.0.dist-info/WHEEL
sbc_drf_notification-1.0.0.dist-info/top_level.txt
sbc_drf_notification-1.0.0.dist-info/zip-safe
sbc_drf_notification-1.0.0.dist-info/RECORD
