Metadata-Version: 2.1
Name: sbc-drf-notification
Version: 1.0.0
Summary: Notification app for SBC project.
Home-page: https://gitlab.stickboycreative.com/sbc-libs/py/sbc_drf_notification
Author: Abhinav Kotak
Author-email: in.abhi9@gmail.com
Maintainer: Abhinav Kotak
Maintainer-email: in.abhi9@gmail.com
License: MIT License
Requires-Dist: sbc-drf (<2,>1)
Requires-Dist: psycopg2-binary
Requires-Dist: djrill (==2.1.0)
